{
    "strategy": "squareGrid",
    "bounds": {
        "horizontal": 10,
        "vertical": 10
    },
    "mapCenter": "b1",
    "initialMapSize": 8,
    "blocks": [{
        "id": "b1",
        "classes": [],
        "connectors": {
            "UP": "none",
            "RIGHT": "none",
            "BOTTOM": "none",
            "LEFT": "none"
        },
        "constraints": {
            "maxOccupation": 5,
            "maxOccupationPercentage": 25
        }
    }, {
        "id": "b2",
        "classes": [],
        "connectors": {
            "UP": "none",
            "RIGHT": "none",
            "BOTTOM": "none",
            "LEFT": "none"
        },
        "constraints": {
            "maxOccupation": 3,
            "maxOccupationPercentage": 25
        }
    }, {
        "id": "b3",
        "classes": [],
        "connectors": {
            "UP": "none",
            "RIGHT": "none",
            "BOTTOM": "none",
            "LEFT": "none"
        },
        "constraints": {}
    }],
    "connectors": [{
        "id": "none",
        "type": "whitelist",
        "blockIds": ["b1", "b2", "b3"],
        "blockClasses": []
    }]
}
